metaframe/__init__.py
metaframe/engine/__init__.py
metaframe/engine/base_engine.py
metaframe/engine/presto_engine.py
metaframe/engine/sql_alchemy_engine.py
metaframe/extractor/__init__.py
metaframe/extractor/amundsen_neo4j_metadata_extractor.py
metaframe/extractor/metadata_service_extractor.py
metaframe/extractor/presto_loop_extractor.py
metaframe/extractor/presto_table_metadata_extractor.py
metaframe/loader/__init__.py
metaframe/loader/metaframe_loader.py
metaframe/models/__init__.py
metaframe/models/connection_config.py
metaframe/models/presto_watermark.py
metaframe/models/table_metadata.py
metaframe/transformer/__init__.py
metaframe/transformer/markdown_transformer.py
metaframe/utils/__init__.py
metaframe/utils/connections.py
metaframe/utils/extractor_wrappers.py
metaframe/utils/neo4j.py
metaframe_databuilder-0.0.0a27.dist-info/METADATA
metaframe_databuilder-0.0.0a27.dist-info/RECORD
metaframe_databuilder-0.0.0a27.dist-info/WHEEL
metaframe_databuilder-0.0.0a27.dist-info/top_level.txt
