Metadata-Version: 2.1
Name: metaframe-databuilder
Version: 0.0.0a27
Summary: A pared-down metadata ETL library, based off amundsen-databuilder.
Home-page: https://github.com/rsyi/metaframe
Author: Robert Yi
Author-email: robert@ryi.me
License: UNKNOWN
Platform: UNKNOWN
Requires-Python: >=3.6
Requires-Dist: amundsen-databuilder (>=2.0.0)
Requires-Dist: pyhocon (>=0.3.42)
Requires-Dist: tabulate
Requires-Dist: pyaml
